rhe-1.0.0.dist-info/RECORD
rhe-1.0.0.dist-info/WHEEL
rhe-1.0.0.dist-info/METADATA
rhe-1.0.0.dist-info/licenses/LICENSE
rhe/GENIE_mem
rhe/runner.py
rhe/GENIE_multi_pheno
rhe/__init__.py
rhe/GENIE
